{"_links":{"self":{"href":"https://eu.api.blizzard.com/data/wow/item/19019?namespace=static-10.2.7_54366-eu"}},"id":19019,"name":{"en_US":"Thunderfury, Blessed Blade of the Windseeker","es_MX":"Trueno Furioso, espada bendita del Hijo del Viento","pt_BR":"Tormentária, Lâmina Sagrada do Perseguidor dos Ventos","de_DE":"Donnerzorn, Gesegnete Klinge des Windsuchers","en_GB":"Thunderfury, Blessed Blade of the Windseeker","es_ES":"Trueno Furioso, Espada Bendita del Hijo del Viento","fr_FR":"Lame-tonnerre, épée bénie du Cherchevent","it_IT":"Furiatonante, Lama Benedetta del Vento Eterno","ru_RU":"Громовая Ярость, благословенный клинок Искателя Ветра","ko_KR":"우레폭풍 - 바람추적자의 성검","zh_TW":"雷霆之怒，逐風者的祝福之刃","zh_CN":"雷霆之怒，逐风者的祝福之剑"},"quality":{"type":"LEGENDARY","name":{"en_US":"Legendary","es_MX":"Legendario","pt_BR":"Lendário","de_DE":"Legendär","en_GB":"Legendary","es_ES":"Legendario","fr_FR":"Légendaire","it_IT":"Leggendario","ru_RU":"Легендарное","ko_KR":"전설","zh_TW":"傳說","zh_CN":"传说"}},"level":29,"required_level":25,"media":{"key":{"href":"https://eu.api.blizzard.com/data/wow/media/item/19019?namespace=static-10.2.7_54366-eu"},"id":19019},"item_class":{"key":{"href":"https://eu.api.blizzard.com/data/wow/item-class/2?namespace=static-10.2.7_54366-eu"},"name":{"en_US":"Weapon","es_MX":"Arma","pt_BR":"Arma","de_DE":"Waffe","en_GB":"Weapon","es_ES":"Arma","fr_FR":"Arme","it_IT":"Arma","ru_RU":"Оружие","ko_KR":"무기","zh_TW":"武器","zh_CN":"武器"},"id":2},"item_subclass":{"key":{"href":"https://eu.api.blizzard.com/data/wow/item-class/2/item-subclass/7?namespace=static-10.2.7_54366-eu"},"name":{"en_US":"Sword","es_MX":"Espada","pt_BR":"Espada","de_DE":"Schwert","en_GB":"Sword","es_ES":"Espada","fr_FR":"Epée","it_IT":"Spada","ru_RU":"Меч","ko_KR":"도검","zh_TW":"劍","zh_CN":"剑"},"id":7},"inventory_type":{"type":"WEAPON","name":{"en_US":"One-Hand","es_MX":"Una mano","pt_BR":"Uma Mão","de_DE":"Einhändig","en_GB":"One-Hand","es_ES":"Una mano","fr_FR":"À une main","it_IT":"Una mano","ru_RU":"Одноручное","ko_KR":"한손 장비","zh_TW":"單手","zh_CN":"单手"}},"purchase_price":162276,"sell_price":32455,"max_count":1,"is_equippable":true,"is_stackable":false,"preview_item":{"item":{"key":{"href":"https://eu.api.blizzard.com/data/wow/item/19019?namespace=static-10.2.7_54366-eu"},"id":19019},"context":0,"bonus_list":[9264],"quality":{"type":"LEGENDARY","name":{"en_US":"Legendary","es_MX":"Legendario","pt_BR":"Lendário","de_DE":"Legendär","en_GB":"Legendary","es_ES":"Legendario","fr_FR":"Légendaire","it_IT":"Leggendario","ru_RU":"Легендарное","ko_KR":"전설","zh_TW":"傳說","zh_CN":"传说"}},"name":{"en_US":"Thunderfury, Blessed Blade of the Windseeker","es_MX":"Trueno Furioso, espada bendita del Hijo del Viento","pt_BR":"Tormentária, Lâmina Sagrada do Perseguidor dos Ventos","de_DE":"Donnerzorn, Gesegnete Klinge des Windsuchers","en_GB":"Thunderfury, Blessed Blade of the Windseeker","es_ES":"Trueno Furioso, Espada Bendita del Hijo del Viento","fr_FR":"Lame-tonnerre, épée bénie du Cherchevent","it_IT":"Furiatonante, Lama Benedetta del Vento Eterno","ru_RU":"Громовая Ярость, благословенный клинок Искателя Ветра","ko_KR":"우레폭풍 - 바람추적자의 성검","zh_TW":"雷霆之怒，逐風者的祝福之刃","zh_CN":"雷霆之怒，逐风者的祝福之剑"},"media":{"key":{"href":"https://eu.api.blizzard.com/data/wow/media/item/19019?namespace=static-10.2.7_54366-eu"},"id":19019},"item_class":{"key":{"href":"https://eu.api.blizzard.com/data/wow/item-class/2?namespace=static-10.2.7_54366-eu"},"name":{"en_US":"Weapon","es_MX":"Arma","pt_BR":"Arma","de_DE":"Waffe","en_GB":"Weapon","es_ES":"Arma","fr_FR":"Arme","it_IT":"Arma","ru_RU":"Оружие","ko_KR":"무기","zh_TW":"武器","zh_CN":"武器"},"id":2},"item_subclass":{"key":{"href":"https://eu.api.blizzard.com/data/wow/item-class/2/item-subclass/7?namespace=static-10.2.7_54366-eu"},"name":{"en_US":"Sword","es_MX":"Espada","pt_BR":"Espada","de_DE":"Schwert","en_GB":"Sword","es_ES":"Espada","fr_FR":"Epée","it_IT":"Spada","ru_RU":"Меч","ko_KR":"도검","zh_TW":"劍","zh_CN":"剑"},"id":7},"inventory_type":{"type":"WEAPON","name":{"en_US":"One-Hand","es_MX":"Una mano","pt_BR":"Uma Mão","de_DE":"Einhändig","en_GB":"One-Hand","es_ES":"Una mano","fr_FR":"À une main","it_IT":"Una mano","ru_RU":"Одноручное","ko_KR":"한손 장비","zh_TW":"單手","zh_CN":"单手"}},"binding":{"type":"ON_ACQUIRE","name":{"en_US":"Binds when picked up","es_MX":"Se liga al recogerlo","pt_BR":"Vincula-se ao ser recolhido","de_DE":"Wird beim Aufheben gebunden","en_GB":"Binds when picked up","es_ES":"Se liga al recogerlo","fr_FR":"Lié quand ramassé","it_IT":"Si vincola alla raccolta","ru_RU":"Становится персональным при получении","ko_KR":"획득 시 귀속","zh_TW":"拾取後綁定","zh_CN":"拾取后绑定"}},"unique_equipped":{"en_US":"Unique","es_MX":"Único","pt_BR":"Único","de_DE":"Einzigartig","en_GB":"Unique","es_ES":"Único","fr_FR":"Unique","it_IT":"Unico","ru_RU":"Уникальный","ko_KR":"고유 아이템","zh_TW":"唯一","zh_CN":"唯一"},"weapon":{"damage":{"min_value":17,"max_value":30,"display_string":{"en_US":"17 - 30 Damage","es_MX":"17 - 30 p. de daño","pt_BR":"17 - 30 de Dano","de_DE":"17 - 30 Schaden","en_GB":"17 - 30 Damage","es_ES":"17 - 30 p. de daño","fr_FR":"Dégâts : 17 - 30","it_IT":"17 - 30 Danni","ru_RU":"Урон: 17 - 30","ko_KR":"공격력 17 ~ 30","zh_TW":"17-30點傷害","zh_CN":"17 - 30点伤害"},"damage_class":{"type":"PHYSICAL","name":{"en_US":"Physical","es_MX":"Físico","pt_BR":"Físico","de_DE":"Körperlich","en_GB":"Physical","es_ES":"Físico","fr_FR":"Physique","it_IT":"Fisico","ru_RU":"физический","ko_KR":"물리","zh_TW":"物理","zh_CN":"物理"}}},"attack_speed":{"value":2600,"display_string":{"en_US":"Speed 2.60","es_MX":"Velocidad 2.60","pt_BR":"Velocidade 2,60","de_DE":"Geschwindigkeit 2,60","en_GB":"Speed 2.60","es_ES":"Velocidad 2,60","fr_FR":"Vitesse 2,60","it_IT":"Velocità 2,60","ru_RU":"Скорость 2,60","ko_KR":"속도 2.60","zh_TW":"速度 2.60","zh_CN":"速度 2.60"}},"dps":{"value":9.038461,"display_string":{"en_US":"(9.0 damage per second)","es_MX":"(9.0 p. de daño por segundo)","pt_BR":"(9,0 de dano por segundo)","de_DE":"(9,0 Schaden pro Sekunde)","en_GB":"(9.0 damage per second)","es_ES":"(9,0 p. de daño por segundo)","fr_FR":"(9,0 dégâts par seconde)","it_IT":"(9,0 danni per secondo)","ru_RU":"(9,0 ед. урона в секунду)","ko_KR":"(초당 공격력 9.0)","zh_TW":"(每秒9.0點傷害)","zh_CN":"（每秒伤害9.0）"}}},"stats":[{"type":{"type":"AGILITY","name":{"en_US":"Agility","es_MX":"agilidad","pt_BR":"Agilidade","de_DE":"Beweglichkeit","en_GB":"Agility","es_ES":"agilidad","fr_FR":"Agilité","it_IT":"Agilità","ru_RU":"к ловкости","ko_KR":"민첩성","zh_TW":"敏捷","zh_CN":"敏捷"}},"value":3,"is_negated":true,"display":{"display_string":{"en_US":"+3 Agility","es_MX":"+3 agilidad","pt_BR":"+3 Agilidade","de_DE":"+3 Beweglichkeit","en_GB":"+3 Agility","es_ES":"+3 agilidad","fr_FR":"+3 Agilité","it_IT":"+3 Agilità","ru_RU":"+3 к ловкости","ko_KR":"민첩성 +3","zh_TW":"+3敏捷","zh_CN":"+3 敏捷"},"color":{"r":128,"g":128,"b":128,"a":1.0}}},{"type":{"type":"STAMINA","name":{"en_US":"Stamina","es_MX":"aguante","pt_BR":"Vigor","de_DE":"Ausdauer","en_GB":"Stamina","es_ES":"aguante","fr_FR":"Endurance","it_IT":"Tempra","ru_RU":"к выносливости","ko_KR":"체력","zh_TW":"耐力","zh_CN":"耐力"}},"value":5,"display":{"display_string":{"en_US":"+5 Stamina","es_MX":"+5 aguante","pt_BR":"+5 Vigor","de_DE":"+5 Ausdauer","en_GB":"+5 Stamina","es_ES":"+5 aguante","fr_FR":"+5 Endurance","it_IT":"+5 Tempra","ru_RU":"+5 к выносливости","ko_KR":"체력 +5","zh_TW":"+5耐力","zh_CN":"+5 耐力"},"color":{"r":255,"g":255,"b":255,"a":1.0}}},{"type":{"type":"FIRE_RESISTANCE","name":{"en_US":"Fire Resistance","es_MX":"Resistencia al Fuego","pt_BR":"Resistência ao Fogo","de_DE":"Feuerwiderstand","en_GB":"Fire Resistance","es_ES":"Resistencia al Fuego","fr_FR":"Résistance au Feu","it_IT":"Resistenza al fuoco","ru_RU":"Сопротивление огню","ko_KR":"화염 저항력","zh_TW":"火焰抗性","zh_CN":"火焰抗性"}},"value":5,"display":{"display_string":{"en_US":"+5 Fire Resistance","es_MX":"+5 resistencia a Fuego","pt_BR":"+5 de resistência a Fogo","de_DE":"+5 Feuerwiderstand","en_GB":"+5 Fire Resistance","es_ES":"+5 resistencia a Fuego","fr_FR":"+5 à la résistance Feu","it_IT":"+5 Resistenza a Fuoco","ru_RU":"+5 к сопротивлению |3-7(огонь)","ko_KR":"화염 저항력 +5","zh_TW":"+5火焰抗性","zh_CN":"+5 火焰抗性"},"color":{"r":0,"g":255,"b":0,"a":1.0}}},{"type":{"type":"NATURE_RESISTANCE","name":{"en_US":"Nature Resistance","es_MX":"Resistencia a la Naturaleza","pt_BR":"Resistência à Natureza","de_DE":"Naturwiderstand","en_GB":"Nature Resistance","es_ES":"Resistencia a la Naturaleza","fr_FR":"Résistance à la Nature","it_IT":"Resistenza alla natura","ru_RU":"Сопротивление силам природы","ko_KR":"자연 저항력","zh_TW":"自然抗性","zh_CN":"自然抗性"}},"value":6,"display":{"display_string":{"en_US":"+6 Nature Resistance","es_MX":"+6 resistencia a Naturaleza","pt_BR":"+6 de resistência a Natureza","de_DE":"+6 Naturwiderstand","en_GB":"+6 Nature Resistance","es_ES":"+6 resistencia a Naturaleza","fr_FR":"+6 à la résistance Nature","it_IT":"+6 Resistenza a Natura","ru_RU":"+6 к сопротивлению |3-7(природа)","ko_KR":"자연 저항력 +6","zh_TW":"+6自然抗性","zh_CN":"+6 自然抗性"},"color":{"r":0,"g":255,"b":0,"a":1.0}}}],"spells":[{"spell":{"key":{"href":"https://eu.api.blizzard.com/data/wow/spell/21992?namespace=static-10.2.7_54366-eu"},"name":{"en_US":"Thunderfury","es_MX":"Trueno Furioso","pt_BR":"Tormentária","de_DE":"Zorn der Winde","en_GB":"Thunderfury","es_ES":"Furiatrueno","fr_FR":"Lame-tonnerre","it_IT":"Furiatonante","ru_RU":"Неистовство бури","ko_KR":"우레폭풍","zh_TW":"雷霆之怒","zh_CN":"雷霆之怒"},"id":21992},"description":{"en_US":"Chance on hit: Blasts your enemy with lightning, dealing 53 Nature damage and then jumping to additional nearby enemies.  Each jump reduces that victim's Nature resistance by 4. Affects 5 targets. Your primary target is also consumed by a cyclone, slowing its attack speed by 20% for 12 sec.","es_MX":"Probabilidad al golpear: Golpea a tu enemigo con relámpagos, inflige 53 p. de daño de Naturaleza. A continuación pasa a otros enemigos cercanos, reduciendo su resistencia a la Naturaleza 4 p. Puede utilizarse sobre 5 objetivos. Además, el primero de los objetivos es golpeado por un ciclón que reduce su velocidad de ataque un 20% durante 12 s.","pt_BR":"Chance ao acertar: Lança raios contra o seu inimigo, causando 53 de dano de Natureza e se propagando para outros inimigos próximos. A propagação para o inimigo seguinte reduz em 4 a resistência à Natureza dele. Afeta 5 alvos. Seu alvo primário também é afetado por um ciclone que reduzirá em 20% a velocidade de ataque por 12 s.","de_DE":"Chance bei Treffer: Deckt Euren Gegner mit Blitzschlägen ein, die 53 Naturschaden verursachen und zu in der Nähe befindlichen Feinden weiterspringen. Jeder Sprung verringert den Naturwiderstand des Ziels um 4. Wirkt auf insgesamt 5 Ziele. Euer Primärziel wird außerdem von einem Wirbelsturm umgeben, welcher dessen Angriffstempo 12 Sek. lang um 20% verringert.","en_GB":"Chance on hit: Blasts your enemy with lightning, dealing 53 Nature damage and then jumping to additional nearby enemies.  Each jump reduces that victim's Nature resistance by 4. Affects 5 targets. Your primary target is also consumed by a cyclone, slowing its attack speed by 20% for 12 sec.","es_ES":"Probabilidad al acertar: Golpea a tu enemigo con relámpagos, inflige 53 p. de daño de Naturaleza. A continuación pasa a otros enemigos cercanos, reduciendo su resistencia a la Naturaleza 4 p. Puede utilizarse sobre 5 objetivos. Además, el primero de los objetivos es golpeado por un ciclón que reduce su velocidad de ataque un 20% durante 12 s.","fr_FR":"Chances quand vous touchez : Votre ennemi est frappé par la foudre, qui lui inflige 53 points de dégâts de Nature avant de passer à d’autres ennemis proches. Chaque rebond réduit de 4 la résistance à la Nature de la victime touchée. Affecte 5 victimes. Votre cible est également engloutie par un cyclone, qui ralentit sa vitesse d’attaque de 20% pendant 12 s.","it_IT":"Probabilità all'impatto: Travolge il nemico con la potenza del fulmine, infliggendo 53 danni da natura e colpendo nemici aggiuntivi vicini. Ogni passaggio riduce la resistenza alla natura del bersaglio di 4. Affligge 5 bersagli. Inoltre, il bersaglio primario viene travolto da un ciclone, che riduce la velocità d'attacco del 20% per 12 s.","ru_RU":"Возможный эффект при попадании: Поражает противника молнией, которая наносит 53 ед. урона от сил природы, после чего перескакивает на других находящихся поблизости противников. Каждый скачок снижает сопротивление силам природы очередной жертвы на 4. Поражает 5 целей. Вашу первую цель также охватывает вихрь, снижая скорость ее атаки на 20% в течение 12 сек.","ko_KR":"발동 효과: 적을 번개로 강타하여 53의 자연 피해를 입히고 주위의 적 5명의 자연 저항력을 4만큼 감소시킵니다. 또한 선택된 대상은 회오리 바람에 휩싸여 12초 동안 공격 속도가 20%만큼 감소합니다.","zh_TW":"擊中時可能： 以閃電的力量攻擊敵人，對其造成53點自然傷害，然後攻擊附近的下一個敵人。閃電每次跳躍都使目標的自然抗性降低4點。可攻擊5個目標。你的目標也會因此被颶風吞噬，使其攻擊間隔時間延長20%，持續12秒。","zh_CN":"击中时可能： 以闪电的力量攻击敌人，对其造成53点自然伤害，然后攻击附近的下一个敌人。闪电每次跳跃都使目标的自然抗性降低4点。可攻击5个目标。你的目标也会因此被飓风吞噬，使其攻击速度降低20%，持续12秒。"}}],"requirements":{"level":{"value":30,"display_string":{"en_US":"Requires Level 30","es_MX":"Necesitas ser de nivel 30","pt_BR":"Requer o Nível 30","de_DE":"Benötigt Stufe 30","en_GB":"Requires Level 30","es_ES":"Necesitas ser de nivel 30","fr_FR":"Niveau 30 requis","it_IT":"Richiede il livello 30","ru_RU":"Требуется 30-й уровень","ko_KR":"최소 요구 레벨: 30","zh_TW":"需要等級30","zh_CN":"需要等级 30"}}},"level":{"value":101,"display_string":{"en_US":"Item Level 101","es_MX":"Nivel de objeto 101","pt_BR":"Nível do Item: 101","de_DE":"Gegenstandsstufe 101","en_GB":"Item Level 101","es_ES":"Nivel de objeto 101","fr_FR":"Niveau d'objet 101","it_IT":"Livello oggetto: 101","ru_RU":"Уровень предмета: 101","ko_KR":"아이템 레벨: 101","zh_TW":"物品等級101","zh_CN":"物品等级101"}},"durability":{"value":130,"display_string":{"en_US":"Durability 130 / 130","es_MX":"Durabilidad 130 / 130","pt_BR":"Durabilidade 130 / 130","de_DE":"Haltbarkeit 130 / 130","en_GB":"Durability 130 / 130","es_ES":"Durabilidad 130 / 130","fr_FR":"Durabilité : 130 / 130","it_IT":"Integrità 130/130","ru_RU":"Прочность: 130 / 130","ko_KR":"내구도 130 / 130","zh_TW":"耐久度 130 / 130","zh_CN":"耐久度 130 / 130"}}},"purchase_quantity":1}